js_lib_vega_embed/__init__.py
js_lib_vega_embed/apps.py
js_lib_vega_embed/static/js_lib_vega_embed/vega-embed-full.js
js_lib_vega_embed/static/js_lib_vega_embed/vega-embed6.js
js_lib_vega_embed/static/js_lib_vega_embed/vega-lite5.js
js_lib_vega_embed/static/js_lib_vega_embed/vega5.js
django_js_lib_vega_embed-6.29.0.3.dist-info/licenses/LICENSE
django_js_lib_vega_embed-6.29.0.3.dist-info/WHEEL
django_js_lib_vega_embed-6.29.0.3.dist-info/METADATA
django_js_lib_vega_embed-6.29.0.3.dist-info/RECORD
