Metadata-Version: 2.4
Name: django-js-lib-vega-embed
Version: 6.29.0.3
Summary: Vega Embed for Django
Classifier: License :: OSI Approved :: MIT License
License-File: LICENSE
